htmls
tests
