Metadata-Version: 1.1
Name: htmls
Version: 2.0.0
Summary: Makes it easy to write use CSS selectors with HTML in your unit tests.
Home-page: https://github.com/espenak/htmls
Author: Espen Angell Kristiansen
Author-email: post@espenak.net
License: BSD
Platform: UNKNOWN
Classifier: Intended Audience :: Developers
Classifier: License :: OSI Approved
Classifier: Programming Language :: Python
